Workbook

Sheet ITC Balance Sheet
A1: Particulars | B1: 41334 | C1: 41699 | D1: 42064 | E1: 42430 | F1: 42795 | G1: 43160 | H1: 43525 | I1: 43891 | J1: 44256 | K1: 44621 | L1: 44986 | M1: 45352 | N1: 45536
A2: Equity Capital | B2: 790 | C2: 795 | D2: 802 | E2: 805 | F2: 1215 | G2: 1220 | H2: 1226 | I2: 1229 | J2: 1231 | K2: 1232 | L2: 1243 | M2: 1248 | N2: 1251
A3: Reserves | B3: 22368 | C3: 26442 | D3: 30934 | E3: 41875 | F3: 45198 | G3: 51290 | H3: 57915 | I3: 64044 | J3: 59116 | K3: 61223 | L3: 67912 | M3: 73259 | N3: 74015
A4: Borrowings - | B4: 102 | C4: 242 | D4: 269 | E4: 84 | F4: 46 | G4: 36 | H4: 13 | I4: 277 | J4: 271 | K4: 249 | L4: 306 | M4: 303 | N4: 304
A5: Long term Borrowings | B5: 91 | C5: 76 | D5: 61 | E5: 27 | F5: 18 | G5: 12 | H5: 8 | I5: 6 | J5: 6 | K5: 5 | L5: 3 | M5: 2 | N5: 2
A6: Short term Borrowings | B6: 0 | C6: 150 | D6: 195 | E6: 44 | F6: 19 | G6: 17 | H6: 2 | I6: 1 | J6: 4 | K6: 1 | L6: 35 | M6: 10 | N6: 25
A7: Lease Liabilities | B7: 0 | C7: 0 | D7: 0 | E7: 0 | F7: 0 | G7: 0 | H7: 0 | I7: 268 | J7: 261 | K7: 244 | L7: 267 | M7: 292 | N7: 278
A8: Other Borrowings | B8: 12 | C8: 16 | D8: 13 | E8: 13 | F8: 8 | G8: 7 | H8: 3 | I8: 2 | J8: 0 | K8: 0 | L8: 0 | M8: 0
A9: Other Liabilities - | B9: 12069 | C9: 13369 | D9: 13948 | E9: 8888 | F9: 9440 | G9: 11695 | H9: 12585 | I9: 11760 | J9: 13143 | K9: 14491 | L9: 16370 | M9: 16944 | N9: 18501
A10: Non controlling int | B10: 180 | C10: 203 | D10: 225 | E10: 261 | F10: 295 | G10: 334 | H10: 343 | I10: 377 | J10: 347 | K10: 366 | L10: 384 | M10: 383 | N10: 526
A11: Trade Payables | B11: 1772 | C11: 2106 | D11: 2020 | E11: 2339 | F11: 2659 | G11: 3496 | H11: 3510 | I11: 3630 | J11: 4319 | K11: 4417 | L11: 4659 | M11: 4798 | N11: 4936
A12: Advance from Customers | B12: 0 | C12: 0 | D12: 0 | E12: 805 | F12: 495 | G12: 461 | H12: 430 | I12: 703 | J12: 811 | K12: 1278 | L12: 1295 | M12: 886
A13: Other liability items | B13: 10118 | C13: 11060 | D13: 11702 | E13: 5483 | F13: 5991 | G13: 7404 | H13: 8301 | I13: 7050 | J13: 7666 | K13: 8429 | L13: 10032 | M13: 10877 | N13: 13038
A14: Total Liabilities | B14: 35329 | C14: 40848 | D14: 45952 | E14: 51651 | F14: 55898 | G14: 64241 | H14: 71739 | I14: 77311 | J14: 73761 | K14: 77196 | L14: 85831 | M14: 91754 | N14: 94071
A15: Fixed Assets - | B15: 12140 | C15: 12921 | D15: 15303 | E15: 15107 | F15: 15893 | G15: 16524 | H15: 19374 | I15: 21713 | J15: 23298 | K15: 24232 | L15: 25851 | M15: 27820 | N15: 29492
A16: Land | B16: 1512 | C16: 1564 | D16: 1717 | E16: 1615 | F16: 1673 | G16: 1685 | H16: 2021 | I16: 2797 | J16: 2889 | K16: 2829 | L16: 2830 | M16: 2865
A17: Building | B17: 3802 | C17: 4110 | D17: 4860 | E17: 4219 | F17: 4716 | G17: 5331 | H17: 6996 | I17: 8161 | J17: 8387 | K17: 9100 | L17: 9789 | M17: 10944
A18: Plant Machinery | B18: 11422 | C18: 12633 | D18: 14667 | E18: 9112 | F18: 10384 | G18: 11453 | H18: 13316 | I18: 14625 | J18: 15307 | K18: 16912 | L18: 18480 | M18: 20718
A19: Equipments | B19: 27 | C19: 34 | D19: 46 | E19: 27 | F19: 32 | G19: 32 | H19: 34 | I19: 40 | J19: 41 | K19: 44 | L19: 44 | M19: 53
A20: Furniture n fittings | B20: 690 | C20: 729 | D20: 805 | E20: 413 | F20: 459 | G20: 497 | H20: 644 | I20: 810 | J20: 833 | K20: 907 | L20: 1000 | M20: 1068
A21: Railway sidings | B21: 2 | C21: 2 | D21: 2 | E21: 2 | F21: 2 | G21: 2 | H21: 2 | I21: 2 | J21: 2 | K21: 2 | L21: 2 | M21: 2
A22: Vehicles | B22: 110 | C22: 120 | D22: 128 | E22: 107 | F22: 128 | G22: 140 | H22: 161 | I22: 184 | J22: 180 | K22: 179 | L22: 189 | M22: 192
A23: Intangible Assets | B23: 418 | C23: 398 | D23: 678 | E23: 563 | F23: 563 | G23: 570 | H23: 684 | I23: 684 | J23: 2734 | K23: 2744 | L23: 3490 | M23: 3505 | N23: 3422
A24: Other fixed assets | B24: 394 | C24: 411 | D24: 458 | E24: 117 | F24: 138 | G24: 212 | H24: 234 | I24: 663 | J24: 716 | K24: 719 | L24: 786 | M24: 841
A25: Gross Block | B25: 18376 | C25: 20000 | D25: 23361 | E25: 16176 | F25: 18094 | G25: 19920 | H25: 24090 | I25: 27965 | J25: 31088 | K25: 33435 | L25: 36608 | M25: 40189
A26: Accumulated Depreciation | B26: 6230 | C26: 7073 | D26: 8057 | E26: 1069 | F26: 2201 | G26: 3396 | H26: 4716 | I26: 6252 | J26: 7790 | K26: 9204 | L26: 10757 | M26: 12368
A27: CWIP | B27: 2062 | C27: 3117 | D27: 2700 | E27: 2560 | F27: 3730 | G27: 5508 | H27: 4136 | I27: 3256 | J27: 4011 | K27: 3226 | L27: 3003 | M27: 2861 | N27: 1387
A28: Investments | B28: 5981 | C28: 7284 | D28: 6943 | E28: 11748 | F28: 17581 | G28: 22053 | H28: 25043 | I28: 28663 | J28: 24871 | K28: 24841 | L28: 29415 | M28: 31114 | N28: 28409
A29: Other Assets - | B29: 15146 | C29: 17526 | D29: 21006 | E29: 22237 | F29: 18694 | G29: 20156 | H29: 23185 | I29: 23678 | J29: 21580 | K29: 24898 | L29: 27561 | M29: 29959 | N29: 34784
A30: Inventories | B30: 7522 | C30: 8255 | D30: 8587 | E30: 9062 | F30: 8116 | G30: 7495 | H30: 7860 | I30: 8879 | J30: 10397 | K30: 10864 | L30: 11771 | M30: 14153 | N30: 17775
A31: Trade receivables | B31: 1396 | C31: 2439 | D31: 1982 | E31: 1917 | F31: 2474 | G31: 2682 | H31: 4035 | I31: 2562 | J31: 2502 | K31: 2462 | L31: 2956 | M31: 4026 | N31: 5825
A32: Cash Equivalents | B32: 3828 | C32: 3490 | D32: 7896 | E32: 6063 | F32: 2967 | G32: 2900 | H32: 4152 | I32: 7277 | J32: 4659 | K32: 4654 | L32: 4880 | M32: 7218 | N32: 5732
A33: Loans n Advances | B33: 65 | C33: 107 | D33: 150 | E33: 14 | F33: 7 | G33: 74 | H33: 67 | I33: 6 | J33: 7 | K33: 11 | L33: 13 | M33: 31 | N33: 1111
A34: Other asset items | B34: 2335 | C34: 3234 | D34: 2391 | E34: 5180 | F34: 5129 | G34: 7004 | H34: 7071 | I34: 4952 | J34: 4015 | K34: 6906 | L34: 7941 | M34: 4531 | N34: 4341
A35: Total Assets | B35: 35329 | C35: 40848 | D35: 45952 | E35: 51651 | F35: 55898 | G35: 64241 | H35: 71739 | I35: 77311 | J35: 73761 | K35: 77196 | L35: 85831 | M35: 91754 | N35: 94071

Sheet ITC Cash flow
B1: 41334 | C1: 41699 | D1: 42064 | E1: 42430 | F1: 42795 | G1: 43160 | H1: 43525 | I1: 43891 | J1: 44256 | K1: 44621 | L1: 44986 | M1: 45352
A2: Cash from Operating Activity - | B2: 7102 | C2: 7344 | D2: 9843 | E2: 9799 | F2: 10627 | G2: 13169 | H2: 12583 | I2: 14690 | J2: 12527 | K2: 15776 | L2: 18878 | M2: 17179
A3: Profit from operations | B3: 11218 | C3: 13172 | D3: 14261 | E3: 15154 | F3: 16075 | G3: 17433 | H3: 18862 | I3: 19416 | J3: 17326 | K3: 20857 | L3: 26052 | M3: 26635
A4: Receivables | B4: -446 | C4: -1546 | D4: 558 | E4: -207 | F4: -870 | G4: -964 | H4: -755 | I4: 1411 | J4: -66 | K4: -732 | L4: -884 | M4: -934
A5: Inventory | B5: -985 | C5: -755 | D5: -505 | E5: -693 | F5: 593 | G5: 602 | H5: -359 | I5: -508 | J5: -1460 | K5: -466 | L5: -1098 | M5: -2545
A6: Payables | B6: 0 | C6: 456 | D6: -23 | E6: 622 | F6: 321 | G6: 2098 | H6: 639 | I6: -607 | J6: 1112 | K6: 1099 | L6: 1058 | M6: 141
A7: Other WC items | B7: 331 | C7: 0 | D7: 0 | E7: 0 | F7: 0 | G7: 0 | H7: 0 | I7: 0 | J7: 0 | K7: 0 | L7: 0 | M7: 0
A8: Working capital changes | B8: -1101 | C8: -1844 | D8: 31 | E8: -277 | F8: 44 | G8: 1736 | H8: -476 | I8: 296 | J8: -413 | K8: -100 | L8: -924 | M8: -3337
A9: Direct taxes | B9: -3015 | C9: -3984 | D9: -4449 | E9: -5078 | F9: -5492 | G9: -6000 | H9: -5803 | I9: -5023 | J9: -4387 | K9: -4982 | L9: -6250 | M9: -6120
A10: Cash from Investing Activity - | B10: -3881 | C10: -3254 | D10: -5275 | E10: -3921 | F10: -3251 | G10: -7114 | H10: -5546 | I10: -6174 | J10: 5740 | K10: -2238 | L10: -5732 | M10: 1563
A11: Fixed assets purchased | B11: -2644 | C11: -2887 | D11: -3300 | E11: -2348 | F11: -3122 | G11: -2878 | H11: -3169 | I11: -2441 | J11: -1837 | K11: -2142 | L11: -2743 | M11: -3563
A12: Fixed assets sold | B12: 10 | C12: 38 | D12: 9 | E12: 8 | F12: 50 | G12: 80 | H12: 28 | I12: 27 | J12: 3 | K12: 133 | L12: 49 | M12: 107
A13: Investments purchased | B13: -75713 | C13: -94242 | D13: -98742 | E13: -154081 | F13: -85683 | G13: -98330 | H13: -94187 | I13: -79835 | J13: -57553 | K13: -69776 | L13: -80932 | M13: -75107
... A29: Net Cash Flow | B29: -90 | C29: -32 | D29: -93 | E29: 266 | F29: 75 | G29: -166 | H29: 169 | I29: 334 | J29: -367 | K29: -43 | L29: 139 | M29: 191

Sheet ITC Income Statement
B1: 41334 | C1: 41699 | D1: 42064 | E1: 42430 | F1: 42795 | G1: 43160 | H1: 43525 | I1: 43891 | J1: 44256 | K1: 44621 | L1: 44986 | M1: 45352 | N1: TTM
A2: Sales - | B2: 31618 | C2: 35306 | D2: 38817 | E2: 39192 | F2: 42768 | G2: 43449 | H2: 48340 | I2: 49388 | J2: 49257 | K2: 60645 | L2: 70919 | M2: 70866 | N2: 75161
A3: Sales Growth % | B3: 0.1924 | C3: 0.1166 | D3: 0.0994 | E3: 0.0097 | F3: 0.0912 | G3: 0.0159 | H3: 0.1126 | I3: 0.0217 | J3: -0.0026 | K3: 0.2312 | L3: 0.1694 | M3: -0.0007
A4: Expenses - | B4: 20398 | C4: 22227 | D4: 24566 | E4: 24661 | F4: 27298 | G4: 26928 | H4: 29802 | I4: 30044 | J4: 32193 | K4: 40021 | L4: 45215 | M4: 44634 | N4: 48872
A5: Material Cost % + | B5: 0.3833 | C5: 0.375 | D5: 0.3806 | E5: 0.3462 | F5: 0.3753 | G5: 0.3649 | H5: 0.3604 | I5: 0.3512 | J5: 0.4087 | K5: 0.4351 | L5: 0.409 | M5: 0.3845
A6: Manufacturing Cost % | B6: 0.0567 | C6: 0.0578 | D6: 0.0552 | E6: 0.0549 | F6: 0.053 | G6: 0.0541 | H6: 0.0542 | I6: 0.0544 | J6: 0.0464 | K6: 0.0458 | L6: 0.0502 | M6: 0.0513
A7: Employee Cost % | B7: 0.0679 | C7: 0.0709 | D7: 0.0714 | E7: 0.0878 | F7: 0.0849 | G7: 0.0866 | H7: 0.0864 | I7: 0.087 | J7: 0.0906 | K7: 0.0806 | L7: 0.0809 | M7: 0.0866
A8: Other Cost % | B8: 0.1373 | C8: 0.1258 | D8: 0.1256 | E8: 0.1403 | F8: 0.1251 | G8: 0.1142 | H8: 0.1156 | I8: 0.1157 | J8: 0.1078 | K8: 0.0984 | L8: 0.0975 | M8: 0.1075
A9: Operating Profit | B9: 11221 | C9: 13080 | D9: 14252 | E9: 14531 | F9: 15470 | G9: 16521 | H9: 18537 | I9: 19344 | J9: 17065 | K9: 20623 | L9: 25704 | M9: 26233 | N9: 26289
A10: OPM % | B10: 0.35 | C10: 0.37 | D10: 0.37 | E10: 0.37 | F10: 0.36 | G10: 0.38 | H10: 0.38 | I10: 0.39 | J10: 0.35 | K10: 0.34 | L10: 0.36 | M10: 0.37 | N10: 0.35
A11: Other Income - | B11: 852 | C11: 966 | D11: 1229 | E11: 1483 | F11: 1759 | G11: 2240 | H11: 2080 | I11: 2417 | J11: 2577 | K11: 1910 | L11: 2098 | M11: 2804 | N11: 2875
A12: Exceptional items | B12: 242 | C12: 326 | D12: 313 | E12: -56 | F12: 136 | G12: 405 | H12: -96 | I12: -189 | J12: -56 | K12: 56 | L12: 68 | M12: 48
A13: Other income normal | B13: 610 | C13: 640 | D13: 916 | E13: 1539 | F13: 1623 | G13: 1835 | H13: 2176 | I13: 2606 | J13: 2633 | K13: 1854 | L13: 2030 | M13: 2755
A14: Interest | B14: 108 | C14: 29 | D14: 91 | E14: 78 | F14: 49 | G14: 115 | H14: 71 | I14: 81 | J14: 58 | K14: 60 | L14: 78 | M14: 80 | N14: 48
A15: Depreciation | B15: 859 | C15: 965 | D15: 1028 | E15: 1077 | F15: 1153 | G15: 1236 | H15: 1397 | I15: 1645 | J15: 1646 | K15: 1732 | L15: 1809 | M15: 1816 | N15: 1792
A16: Profit before tax | B16: 11106 | C16: 13052 | D16: 14362 | E16: 14859 | F16: 16026 | G16: 17409 | H16: 19150 | I16: 20035 | J16: 17938 | K16: 20740 | L16: 25915 | M16: 27140 | N16: 27323
A17: Tax % | B17: 0.31 | C17: 0.31 | D17: 0.32 | E17: 0.36 | F17: 0.35 | G17: 0.34 | H17: 0.33 | I17: 0.22 | J17: 0.25 | K17: 0.25 | L17: 0.25 | M17: 0.24
A18: Net Profit - | B18: 7704 | C18: 9001 | D18: 9779 | E18: 9501 | F18: 10477 | G18: 11493 | H18: 12836 | I18: 15593 | J18: 13383 | K18: 15503 | L18: 19477 | M18: 20751 | N18: 20435
A19: Profit after tax | B19: 7694 | C19: 8991 | D19: 9766 | E19: 9501 | F19: 10477 | G19: 11493 | H19: 12836 | I19: 15593 | J19: 13383 | K19: 15503 | L19: 19477 | M19: 20751
A20: Profit from Associates | B20: 11 | C20: 11 | D20: 13 | E20: 0 | F20: 0 | G20: 0 | H20: 0 | I20: 0 | J20: 0 | K20: 0 | L20: 0 | M20: 0
A21: Reported Net Profit | B21: 7704 | C21: 9001 | D21: 9779 | E21: 9501 | F21: 10477 | G21: 11493 | H21: 12836 | I21: 15593 | J21: 13383 | K21: 15503 | L21: 19477 | M21: 20751
A22: Minority share | B22: -96 | C22: -110 | D22: -115 | E22: -156 | F22: -188 | G22: -221 | H22: -244 | I22: -287 | J22: -222 | K22: -260 | L22: -285 | M22: -293
A23: Profit for EPS | B23: 7608 | C23: 8891 | D23: 9663 | E23: 9344 | F23: 10289 | G23: 11271 | H23: 12592 | I23: 15306 | J23: 13161 | K23: 15243 | L23: 19192 | M23: 20459
A24: Exceptional items AT | B24: 168 | C24: 222 | D24: 214 | E24: -36 | F24: 89 | G24: 262 | H24: -64 | I24: -142 | J24: -41 | K24: 42 | L24: 51 | M24: 37
A25: Profit for PE | B25: 7442 | C25: 8672 | D25: 9452 | E25: 9380 | F25: 10203 | G25: 11014 | H25: 12655 | I25: 15446 | J25: 13202 | K25: 15202 | L25: 19141 | M25: 20422
A26: EPS in Rs | B26: 6.42 | C26: 7.45 | D26: 8.04 | E26: 7.74 | F26: 8.47 | G26: 9.24 | H26: 10.27 | I26: 12.45 | J26: 10.69 | K26: 12.37 | L26: 15.44 | M26: 16.39 | N26: 16.11
A27: Dividend Payout % | B27: 0.55 | C27: 0.54 | D27: 0.52 | E27: 0.73 | F27: 0.56 | G27: 0.56 | H27: 0.56 | I27: 0.82 | J27: 1.01 | K27: 0.93 | L27: 1 | M27: 0.84

Sheet Duopont
A2: ITC Ltd ₹ 412 BSE:500857 | D2: #VALUE! | H2: DuPont Summary
A4: DuPont Analysis
H30: Recent Updates (2025)
A44: Return On Equity (ROE)
B45: 43525 | C45: 43891 | D45: 44256 | E45: 44621 | F45: 44986 | G45: 45352
A46: Net Profit | B46: ='ITC Income Statement'!H18 -> 12836 | C46: ='ITC Income Statement'!I18 -> 15593 | D46: ='ITC Income Statement'!J18 -> 13383 | E46: ='ITC Income Statement'!K18 -> 15503 | F46: ='ITC Income Statement'!L18 -> 19477 | G46: ='ITC Income Statement'!M18 -> 20751
A47: Avg Sh. Equity | B47: =(('ITC Balance Sheet'!H2+'ITC Balance Sheet'!H3)+('ITC Balance Sheet'!G2+'ITC Balance Sheet'!G3))/2 -> 55825.5 | C47: =(('ITC Balance Sheet'!I2+'ITC Balance Sheet'!I3)+('ITC Balance Sheet'!H2+'ITC Balance Sheet'!H3))/2 -> 62207 | D47: =(('ITC Balance Sheet'!J2+'ITC Balance Sheet'!J3)+('ITC Balance Sheet'!I2+'ITC Balance Sheet'!I3))/2 -> 62810 | E47: =(('ITC Balance Sheet'!K2+'ITC Balance Sheet'!K3)+('ITC Balance Sheet'!J2+'ITC Balance Sheet'!J3))/2 -> 61401 | F47: =(('ITC Balance Sheet'!L2+'ITC Balance Sheet'!L3)+('ITC Balance Sheet'!K2+'ITC Balance Sheet'!K3))/2 -> 65805 | G47: =(('ITC Balance Sheet'!M2+'ITC Balance Sheet'!M3)+('ITC Balance Sheet'!L2+'ITC Balance Sheet'!L3))/2 -> 71831
A48: Return On Equity (ROE) | B48: =B46/B47 -> 0.22993077 | C48: =C46/C47 -> 0.25066311 | D48: =D46/D47 -> 0.21307117 | E48: =E46/E47 -> 0.25248774 | F48: =F46/F47 -> 0.29598055 | G48: =G46/G47 -> 0.28888641
A50: DuPont Equation (ROE)
B51: 43525 | C51: 43891 | D51: 44256 | E51: 44621 | F51: 44986 | G51: 45352
A52: Net Profit | B52: 12836 | C52: 15593 | D52: 13383 | E52: 15503 | F52: 19477 | G52: 20751
A53: Revenue | B53: ='ITC Income Statement'!H2 -> 48340 | C53: ='ITC Income Statement'!I2 -> 49388 | D53: ='ITC Income Statement'!J2 -> 49257 | E53: ='ITC Income Statement'!K2 -> 60645 | F53: ='ITC Income Statement'!L2 -> 70919 | G53: ='ITC Income Statement'!M2 -> 70866
A54: Net Profit Margin (A) | B54: =B52/B53 -> 0.26553579 | C54: =C52/C53 -> 0.31572447 | D54: =D52/D53 -> 0.27169742 | E54: =E52/E53 -> 0.25563525 | F54: =F52/F53 -> 0.27463726 | G54: =G52/G53 -> 0.29282025
A56: Revenue | B56: =B53 -> 48340 | C56: =C53 -> 49388 | D56: =D53 -> 49257 | E56: =E53 -> 60645 | F56: =F53 -> 70919 | G56: =G53 -> 70866
A57: Average Total Assets | B57: =('ITC Balance Sheet'!H35+'ITC Balance Sheet'!G35)/2 -> 67990 | C57: =('ITC Balance Sheet'!I35+'ITC Balance Sheet'!H35)/2 -> 74525 | D57: =('ITC Balance Sheet'!J35+'ITC Balance Sheet'!I35)/2 -> 75536 | E57: =('ITC Balance Sheet'!K35+'ITC Balance Sheet'!J35)/2 -> 75478.5 | F57: =('ITC Balance Sheet'!L35+'ITC Balance Sheet'!K35)/2 -> 81513.5 | G57: =('ITC Balance Sheet'!M35+'ITC Balance Sheet'!L35)/2 -> 88792.5
A58: Average Turnover Ratio (B) | B58: =B56/B57 -> 0.71098691 | C58: =C56/C57 -> 0.66270379 | D58: =D56/D57 -> 0.65209966 | E58: =E56/E57 -> 0.80347384 | F58: =F56/F57 -> 0.87002766 | G58: =G56/G57 -> 0.79810795
A60: Average Total Assets | B60: =B57 -> 67990 | C60: =C57 -> 74525 | D60: =D57 -> 75536 | E60: =E57 -> 75478.5 | F60: =F57 -> 81513.5 | G60: =G57 -> 88792.5
A61: Avg Sh. Equity | B61: =B47 -> 55825.5 | C61: =C47 -> 62207 | D61: =D47 -> 62810 | E61: =E47 -> 61401 | F61: =F47 -> 65805 | G61: =G47 -> 71831
A62: Financial Leverage (C) | B62: =B60/B61 -> 1.2179022 | C62: =C60/C61 -> 1.1980163 | D62: =D60/D61 -> 1.202611 | E62: =E60/E61 -> 1.2292715 | F62: =F60/F61 -> 1.2387129 | G62: =G60/G61 -> 1.2361306
A64: Return On Equity (A*B*C) | B64: =B62*B58*B54 -> 0.22993077 | C64: =C62*C58*C54 -> 0.25066311 | D64: =D62*D58*D54 -> 0.21307117 | E64: =E62*E58*E54 -> 0.25248774 | F64: =F62*F58*F54 -> 0.29598055 | G64: =G62*G58*G54 -> 0.28888641
A66: Return On Asset (ROA)
B67: 43525 | C67: 43891 | D67: 44256 | E67: 44621 | F67: 44986 | G67: 45352
A68: Net Profit | B68: =B52 -> 12836 | C68: =C52 -> 15593 | D68: =D52 -> 13383 | E68: =E52 -> 15503 | F68: =F52 -> 19477 | G68: =G52 -> 20751
A69: =A57 -> Average Total Assets | B69: =B57 -> 67990 | C69: =C57 -> 74525 | D69: =D57 -> 75536 | E69: =E57 -> 75478.5 | F69: =F57 -> 81513.5 | G69: =G57 -> 88792.5
A70: Return On Asset(ROA) | B70: =B68/B69 -> 0.18879247 | C70: =C68/C69 -> 0.2092318 | D70: =D68/D69 -> 0.1771738 | E70: =E68/E69 -> 0.20539624 | F70: =F68/F69 -> 0.23894202 | G70: =G68/G69 -> 0.23370217
A72: DuPont Equation (ROA)
B73: 43525 | C73: 43891 | D73: 44256 | E73: 44621 | F73: 44986 | G73: 45352
A74: Net Profit | B74: =B68 -> 12836 | C74: =C68 -> 15593 | D74: =D68 -> 13383 | E74: =E68 -> 15503 | F74: =F68 -> 19477 | G74: =G68 -> 20751
A75: Revenue | B75: =B56 -> 48340 | C75: =C56 -> 49388 | D75: =D56 -> 49257 | E75: =E56 -> 60645 | F75: =F56 -> 70919 | G75: =G56 -> 70866
A76: Net Profit Margin (A) | B76: =B74/B75 -> 0.26553579 | C76: =C74/C75 -> 0.31572447 | D76: =D74/D75 -> 0.27169742 | E76: =E74/E75 -> 0.25563525 | F76: =F74/F75 -> 0.27463726 | G76: =G74/G75 -> 0.29282025
A78: Revenue | B78: =B75 -> 48340 | C78: =C75 -> 49388 | D78: =D75 -> 49257 | E78: =E75 -> 60645 | F78: =F75 -> 70919 | G78: =G75 -> 70866
A79: Average Total Assets | B79: =B69 -> 67990 | C79: =C69 -> 74525 | D79: =D69 -> 75536 | E79: =E69 -> 75478.5 | F79: =F69 -> 81513.5 | G79: =G69 -> 88792.5
A80: Average Turnover Ratio (B) | B80: =B78/B79 -> 0.71098691 | C80: =C78/C79 -> 0.66270379 | D80: =D78/D79 -> 0.65209966 | E80: =E78/E79 -> 0.80347384 | F80: =F78/F79 -> 0.87002766 | G80: =G78/G79 -> 0.79810795
A82: Return On Equity (A*B) | B82: =B76*B80 -> 0.18879247 | C82: =C76*C80 -> 0.2092318 | D82: =D76*D80 -> 0.1771738 | E82: =E76*E80 -> 0.20539624 | F82: =F76*F80 -> 0.23894202 | G82: =G76*G80 -> 0.23370217
